cherab/phix/VERSION
cherab/phix/__init__.py
cherab/phix/tools/laplacian.cpython-39-x86_64-linux-gnu.so
cherab/phix/tools/laplacian.pyx
cherab/phix/tools/utils.py
cherab/phix/tools/__init__.py
cherab/phix/tools/visualize.py
cherab/phix/tools/raytransfer.py
cherab/phix/tools/spinner.py
cherab/phix/inversion/lcurve.py
cherab/phix/inversion/gcv.py
cherab/phix/inversion/__init__.py
cherab/phix/inversion/inversion.py
cherab/phix/inversion/test/test.py
cherab/phix/machine/wall_outline.py
cherab/phix/machine/__init__.py
cherab/phix/machine/pfc_mesh.py
cherab/phix/machine/material/dielectric.py
cherab/phix/machine/material/__init__.py
cherab/phix/machine/material/metal.py
cherab/phix/machine/material/roughmetal.py
cherab/phix/machine/material/data/PCTFE.json
cherab/phix/machine/material/data/sus316L.json
cherab/phix/machine/geometry/format_cad_file.py
cherab/phix/machine/geometry/data/PHiX_calcam_CAD.ccm
cherab/phix/machine/geometry/data/RSMfiles/limiter_225.rsm
cherab/phix/machine/geometry/data/RSMfiles/FBC_half_down.rsm
cherab/phix/machine/geometry/data/RSMfiles/vessel_gasket_half.rsm
cherab/phix/machine/geometry/data/RSMfiles/rail_half_up.rsm
cherab/phix/machine/geometry/data/RSMfiles/limiter_box.rsm
cherab/phix/machine/geometry/data/RSMfiles/vessel_wall_fine.rsm
cherab/phix/machine/geometry/data/RSMfiles/FBC_half_up.rsm
cherab/phix/machine/geometry/data/RSMfiles/rail_connection_half.rsm
cherab/phix/machine/geometry/data/RSMfiles/FL_half.rsm
cherab/phix/machine/geometry/data/RSMfiles/MG_port.rsm
cherab/phix/machine/geometry/data/RSMfiles/vaccum_flange.rsm
cherab/phix/machine/geometry/data/RSMfiles/rail_half_down.rsm
cherab/phix/machine/geometry/data/RSMfiles/vessel_wall.rsm
cherab/phix/machine/geometry/data/STLfiles/FL_half2.STL
cherab/phix/machine/geometry/data/STLfiles/FBC_half_down2.STL
cherab/phix/machine/geometry/data/STLfiles/MG_port.STL
cherab/phix/machine/geometry/data/STLfiles/rail_half_down2.STL
cherab_phix-1.1.0.dist-info/top_level.txt
cherab_phix-1.1.0.dist-info/WHEEL
cherab_phix-1.1.0.dist-info/RECORD
cherab_phix-1.1.0.dist-info/METADATA
cherab_phix-1.1.0.dist-info/LICENSE.md
cherab_phix-1.1.0.dist-info/AUTHORS.md
