Metadata-Version: 2.1
Name: cherab-phix
Version: 1.1.0
Summary: Cherab spectroscopy framework: PHiX machine configuration
Author-email: Koyo Munechika <munechika.koyo@torus.nr.titech.ac.jp>
Maintainer-email: Koyo Munechika <munechika.koyo@torus.nr.titech.ac.jp>
License: BSD 3-Clause License
Project-URL: Homepage, https://cherab-phix.readthedocs.io/
Project-URL: documentation, https://cherab-phix.readthedocs.io/
Project-URL: repository, https://github.com/munechika-koyo/cherab_phix
Classifier: Development Status :: 5 - Production/Stable
Classifier: Intended Audience :: Science/Research
Classifier: Intended Audience :: Education
Classifier: Intended Audience :: Developers
Classifier: License :: OSI Approved :: BSD License
Classifier: Natural Language :: English
Classifier: Operating System :: POSIX :: Linux
Classifier: Programming Language :: Cython
Classifier: Programming Language :: Python :: 3.8
Classifier: Programming Language :: Python :: 3.9
Classifier: Topic :: Scientific/Engineering :: Physics
Requires-Python: <3.10,>=3.8
License-File: LICENSE.md
License-File: AUTHORS.md
Requires-Dist: numpy
Requires-Dist: scipy
Requires-Dist: matplotlib <3.6
Requires-Dist: contourpy
Requires-Dist: plotly
Requires-Dist: numpy-stl
Requires-Dist: cherab ==1.4.0
Requires-Dist: calcam
Provides-Extra: dev
Requires-Dist: ipython ; extra == 'dev'
Requires-Dist: black ; extra == 'dev'
Requires-Dist: ruff ; extra == 'dev'
Requires-Dist: mypy ; extra == 'dev'
Requires-Dist: rich-click ; extra == 'dev'
Requires-Dist: cython-lint ; extra == 'dev'
Requires-Dist: pre-commit ; extra == 'dev'
Requires-Dist: cython >=3.0 ; extra == 'dev'
Provides-Extra: docs
Requires-Dist: docutils ; extra == 'docs'
Requires-Dist: ipykernel ; extra == 'docs'
Requires-Dist: ipywidgets ; extra == 'docs'
Requires-Dist: jinja2 <3.1 ; extra == 'docs'
Requires-Dist: nbconvert >=7.3 ; extra == 'docs'
Requires-Dist: nbsphinx ; extra == 'docs'
Requires-Dist: pillow ; extra == 'docs'
Requires-Dist: pygments >=2.11.0 ; extra == 'docs'
Requires-Dist: sphinx >=5 ; extra == 'docs'
Requires-Dist: sphinx-prompt ; extra == 'docs'
Requires-Dist: sphinx-copybutton ; extra == 'docs'
Requires-Dist: pydata-sphinx-theme <0.14 ; extra == 'docs'
Requires-Dist: sphinx-design ; extra == 'docs'
Requires-Dist: pandoc ; extra == 'docs'
Requires-Dist: sphinx-codeautolink ; extra == 'docs'
Requires-Dist: sphinx-github-style ; extra == 'docs'
